cgrputil/__init__.py
cgrputil/cgrputil.py
cgrputil-1.0.1.data/data/LICENSE/LICENSE
cgrputil-1.0.1.data/data/README/README.md
cgrputil-1.0.1.dist-info/LICENSE
cgrputil-1.0.1.dist-info/METADATA
cgrputil-1.0.1.dist-info/WHEEL
cgrputil-1.0.1.dist-info/top_level.txt
cgrputil-1.0.1.dist-info/RECORD
