Metadata-Version: 2.1
Name: cgrputil
Version: 1.0.1
Summary: Package to calculate cpu utilisation in cgroups
Home-page: https://github.com/rushi47/cgrputil
Author: Rushikesh Butley
Author-email: rushikeshbutley@gmail.com
License: MIT
Platform: UNKNOWN
Classifier: Environment :: Console
Classifier: Environment :: Other Environment
Classifier: Environment :: Plugins
Classifier: Intended Audience :: Developers
Classifier: Intended Audience :: System Administrators
Classifier: Operating System :: POSIX :: Linux
Classifier: Operating System :: Unix
Classifier: Programming Language :: Python :: 2.7
Classifier: Programming Language :: Python :: 3
Classifier: Topic :: System
Requires-Python: >=2.7
